LICENSE.txt
MANIFEST.in
README.md
setup.py
categorium/__init__.py
categorium/csv_utils.py
categorium/model_utils.py
categorium/test_model_utils.py
categorium/token_utils.py
categorium/train_utils.py
categorium.egg-info/PKG-INFO
categorium.egg-info/SOURCES.txt
categorium.egg-info/dependency_links.txt
categorium.egg-info/requires.txt
categorium.egg-info/top_level.txt
categorium/modelos/de/de_categorias.csv
categorium/modelos/de/hultig-bert-token-uncased_de-vocab.txt
categorium/modelos/de/de_hultig_model/config.json
categorium/modelos/de/de_hultig_model/tf_model.h5
categorium/modelos/en/en_categorias.csv
categorium/modelos/en/hultig-bert-token-uncased_en-vocab.txt
categorium/modelos/en/en_hultig_model/config.json
categorium/modelos/en/en_hultig_model/tf_model.h5
categorium/modelos/es/es_categorias.csv
categorium/modelos/es/hultig-bert-token-uncased_es-vocab.txt
categorium/modelos/es/es_hultig_model/config.json
categorium/modelos/es/es_hultig_model/tf_model.h5
categorium/modelos/fr/fr_categorias.csv
categorium/modelos/fr/hultig-bert-token-uncased_fr-vocab.txt
categorium/modelos/fr/fr_hultig_model/config.json
categorium/modelos/fr/fr_hultig_model/tf_model.h5
categorium/modelos/it/hultig-bert-token-uncased_it-vocab.txt
categorium/modelos/it/it_categorias.csv
categorium/modelos/it/it_hultig_model/config.json
categorium/modelos/it/it_hultig_model/tf_model.h5
categorium/modelos/pt/hultig-bert-token-uncased_pt-vocab.txt
categorium/modelos/pt/pt_categorias.csv
categorium/modelos/pt/pt_hultig_model/config.json
categorium/modelos/pt/pt_hultig_model/tf_model.h5