Metadata-Version: 2.1
Name: categorium
Version: 0.2.2
Summary: A package for creating and training language models for text classification based on BERT. The package includes pre-trained models and a feature for testing the trained models.
Author: Luís Silva
Author-email: <aluisgonalo022@gmail.com>
Keywords: python,classification,text,Categorization,textCategorization,textclassification,BERT
Classifier: Development Status :: 1 - Planning
Classifier: Intended Audience :: Developers
Classifier: Programming Language :: Python :: 3
Classifier: Operating System :: Unix
Classifier: Operating System :: MacOS :: MacOS X
Classifier: Operating System :: Microsoft :: Windows
License-File: LICENSE.txt
